cz_ru.py
cz_ru-0.1.4.dist-info/LICENSE
cz_ru-0.1.4.dist-info/METADATA
cz_ru-0.1.4.dist-info/WHEEL
cz_ru-0.1.4.dist-info/entry_points.txt
cz_ru-0.1.4.dist-info/RECORD
