Metadata-Version: 2.1
Name: cz-ru
Version: 0.1.4
Summary: Russian config for Commitizen based on Conventional Commits
Home-page: https://github.com/teatov/cz-ru
License: MIT
Author: teatov
Author-email: teatov@proton.me
Requires-Python: >=3.11,<4.0
Classifier: License :: OSI Approved :: MIT License
Classifier: Programming Language :: Python :: 3
Classifier: Programming Language :: Python :: 3.11
Classifier: Programming Language :: Python :: 3.12
Classifier: Programming Language :: Python :: 3.13
Requires-Dist: commitizen (>=3.30.0,<4.0.0)
Project-URL: Repository, https://github.com/teatov/cz-ru
